elements/__init__.py
elements/core/__init__.py
elements/core/account.py
elements/core/app.py
elements/core/collection.py
elements/core/config.py
elements/core/core.py
elements/core/database.py
elements/core/event.py
elements/core/integrations.py
elements/core/session.py
elements/core/tagdict.py
elements/core/timestamp.py
elements/lenses/.autonomy.py.swp
elements/lenses/.canvas.py.swp
elements/lenses/README.md
elements/lenses/__init__.py
elements/lenses/autonomy.py
elements/lenses/canvas.py
elements/lenses/sessions.py
elements/lenses/social.py
elements/libs/README.md
elements/libs/base58.py
elements/libs/bech32.py
elements/libs/bip32/__init__.py
elements/libs/bip32/bip32.py
elements/libs/bip32/ripemd160.py
elements/libs/bip32/utils.py
elements/libs/bottle.py
elements/libs/chacha.py
elements/libs/chevron/__init__.py
elements/libs/chevron/main.py
elements/libs/chevron/metadata.py
elements/libs/chevron/renderer.py
elements/libs/chevron/tokenizer.py
elements/libs/encryption.py
elements/libs/markdown/__init__.py
elements/libs/markdown/__main__.py
elements/libs/markdown/__meta__.py
elements/libs/markdown/blockparser.py
elements/libs/markdown/blockprocessors.py
elements/libs/markdown/core.py
elements/libs/markdown/extensions/__init__.py
elements/libs/markdown/extensions/abbr.py
elements/libs/markdown/extensions/admonition.py
elements/libs/markdown/extensions/attr_list.py
elements/libs/markdown/extensions/codehilite.py
elements/libs/markdown/extensions/def_list.py
elements/libs/markdown/extensions/extra.py
elements/libs/markdown/extensions/fenced_code.py
elements/libs/markdown/extensions/footnotes.py
elements/libs/markdown/extensions/legacy_attrs.py
elements/libs/markdown/extensions/legacy_em.py
elements/libs/markdown/extensions/md_in_html.py
elements/libs/markdown/extensions/meta.py
elements/libs/markdown/extensions/nl2br.py
elements/libs/markdown/extensions/sane_lists.py
elements/libs/markdown/extensions/smarty.py
elements/libs/markdown/extensions/tables.py
solar_elements-0.3.0.dist-info/METADATA
solar_elements-0.3.0.dist-info/WHEEL
solar_elements-0.3.0.dist-info/RECORD
