Metadata-Version: 2.3
Name: solar-elements
Version: 0.3.0
Summary: Python library for interacting with the Solar System
Author: Zen
Author-email: zen@credenso.cafe
Requires-Python: >=3.11,<4.0
Classifier: Programming Language :: Python :: 3
Classifier: Programming Language :: Python :: 3.11
Classifier: Programming Language :: Python :: 3.12
Classifier: Programming Language :: Python :: 3.13
Requires-Dist: chevron (>=0.14.0,<0.15.0)
Requires-Dist: markdown (>=3.7,<4.0)
Requires-Dist: pillow (>=11.0.0,<12.0.0)
Requires-Dist: pycryptodome (>=3.21.0,<4.0.0)
Requires-Dist: secp256k1 (>=0.14.0,<0.15.0)
Requires-Dist: websockets (>=15.0.1,<16.0.0)
